LICENSE
README.md
pyproject.toml
src/rsspolymlp/__init__.py
src/rsspolymlp.egg-info/PKG-INFO
src/rsspolymlp.egg-info/SOURCES.txt
src/rsspolymlp.egg-info/dependency_links.txt
src/rsspolymlp.egg-info/entry_points.txt
src/rsspolymlp.egg-info/requires.txt
src/rsspolymlp.egg-info/top_level.txt
src/rsspolymlp/analysis/__init__.py
src/rsspolymlp/analysis/eos.py
src/rsspolymlp/analysis/ghost_minima.py
src/rsspolymlp/analysis/load_plot_data.py
src/rsspolymlp/analysis/phase_analysis.py
src/rsspolymlp/analysis/rss_summarize.py
src/rsspolymlp/analysis/unique_struct.py
src/rsspolymlp/analysis/struct_matcher/__init__.py
src/rsspolymlp/analysis/struct_matcher/chiral_spg.py
src/rsspolymlp/analysis/struct_matcher/invert_and_swap.py
src/rsspolymlp/analysis/struct_matcher/reduced_position.py
src/rsspolymlp/analysis/struct_matcher/struct_match.py
src/rsspolymlp/analysis/struct_matcher/deprecated/invert_and_swap.py
src/rsspolymlp/analysis/struct_matcher/deprecated/irrep_position.py
src/rsspolymlp/analysis/struct_matcher/deprecated/niggli.py
src/rsspolymlp/analysis/struct_matcher/deprecated/struct_match.py
src/rsspolymlp/analysis/struct_matcher/deprecated/utils.py
src/rsspolymlp/api/__init__.py
src/rsspolymlp/api/cli_rsspolymlp.py
src/rsspolymlp/api/cli_rsspolymlp_devkit.py
src/rsspolymlp/api/cli_rsspolymlp_plot.py
src/rsspolymlp/api/cli_rsspolymlp_utils.py
src/rsspolymlp/api/rsspolymlp.py
src/rsspolymlp/api/rsspolymlp_devkit.py
src/rsspolymlp/api/rsspolymlp_plot.py
src/rsspolymlp/api/rsspolymlp_utils.py
src/rsspolymlp/common/__init__.py
src/rsspolymlp/common/atomic_energy.py
src/rsspolymlp/common/composition.py
src/rsspolymlp/common/convert_dict.py
src/rsspolymlp/common/property.py
src/rsspolymlp/mlp_dev/estimate_cost.py
src/rsspolymlp/mlp_dev/pareto_opt_mlp.py
src/rsspolymlp/mlp_dev/polymlp_dev.py
src/rsspolymlp/mlp_dev/dataset/compress_vasprun.py
src/rsspolymlp/mlp_dev/dataset/divide_dataset.py
src/rsspolymlp/mlp_dev/dataset/gen_mlp_dataset.py
src/rsspolymlp/mlp_dev/model_selection/gen_hybrid_model.py
src/rsspolymlp/mlp_dev/model_selection/gen_single_model.py
src/rsspolymlp/mlp_dev/model_selection/n_feature.py
src/rsspolymlp/mlp_dev/model_selection/pypolymlp_gridsearch.py
