Metadata-Version: 2.4
Name: rsspolymlp
Version: 0.3.0
Summary: A framework for random structure search using polynomial MLPs
Author-email: Hayato Wakai <wakai@cms.mtl.kyoto-u.ac.jp>
Maintainer-email: Hayato Wakai <wakai@cms.mtl.kyoto-u.ac.jp>
License-Expression: MIT
Project-URL: homepage, https://github.com/hytwakai/rsspolymlp
Project-URL: repository, https://github.com/hytwakai/rsspolymlp
Requires-Python: >=3.10
License-File: LICENSE
Requires-Dist: numpy
Requires-Dist: scipy
Requires-Dist: scikit-learn
Requires-Dist: joblib
Requires-Dist: pypolymlp
Requires-Dist: spglib
Requires-Dist: symfc
Provides-Extra: pymatgen
Requires-Dist: pymatgen; extra == "pymatgen"
Provides-Extra: matplotlib
Requires-Dist: matplotlib; extra == "matplotlib"
Provides-Extra: seaborn
Requires-Dist: seaborn; extra == "seaborn"
Provides-Extra: tools
Requires-Dist: pymatgen; extra == "tools"
Requires-Dist: matplotlib; extra == "tools"
Requires-Dist: seaborn; extra == "tools"
Dynamic: license-file
